imuthes/alchemy/columns/.git
imuthes/alchemy/columns/README.md
imuthes/alchemy/columns/__init__.py
imuthes/alchemy/columns/default_flag.py
imuthes/alchemy/columns/default_record_not_found_error.py
imuthes/alchemy/columns/description.py
imuthes/alchemy/columns/named.py
imuthes/alchemy/columns/notes.py
imuthes/alchemy/columns/system_flag.py
imuthes_alchemy_columns-0.0.0a8.dist-info/METADATA
imuthes_alchemy_columns-0.0.0a8.dist-info/WHEEL
imuthes_alchemy_columns-0.0.0a8.dist-info/RECORD
