Metadata-Version: 2.3
Name: imuthes-alchemy-columns
Version: 0.0.0a8
Summary: SQL Alchemy Columns
License: LGPL-3.0-or-later
Keywords: tools
Author: Bernhard Radermacher
Author-email: bernhard.radermacher@netlink-consulting.com
Requires-Python: >=3.11,<4.0
Classifier: Development Status :: 3 - Alpha
Classifier: Intended Audience :: Developers
Classifier: License :: OSI Approved :: GNU Lesser General Public License v3 or later (LGPLv3+)
Classifier: Programming Language :: Python :: 3.11
Classifier: Programming Language :: Python :: 3.12
Classifier: Programming Language :: Python :: 3.13
Classifier: Topic :: Software Development
Classifier: Topic :: Utilities
Classifier: Typing :: Typed
Requires-Dist: hakisto (>=0.3.4a6,<0.4.0)
Requires-Dist: imuthes-alchemy (>=0.0.0a8,<0.0.1)
Requires-Dist: setuptools (>=78.1.0,<79.0.0)
Project-URL: Repository, https://gitlab.com/imuthes-py/imuthes-alchemy-columns
